ko_pron/__init__.py
ko_pron/data.py
ko_pron/ko_pron.py
ko_pron-1.2.dist-info/METADATA
ko_pron-1.2.dist-info/RECORD
ko_pron-1.2.dist-info/WHEEL
ko_pron-1.2.dist-info/top_level.txt
