Metadata-Version: 2.1
Name: ko-pron
Version: 1.2
Summary: Korean pronunciation and romanisation based on Wiktionary ko-pron lua module
Home-page: UNKNOWN
Author: Andriy Koretskyy
Author-email: kord123@gmail.com
License: MIT
Keywords: hangul korean pronunciation romanisation romanization IPA Yale McCune-Reischauer WT-revised revised
Platform: UNKNOWN
Classifier: Programming Language :: Python :: 3
Classifier: Operating System :: OS Independent
